sitemapa/__init__.py
sitemapa-0.1.4.dist-info/LICENSE
sitemapa-0.1.4.dist-info/METADATA
sitemapa-0.1.4.dist-info/WHEEL
sitemapa-0.1.4.dist-info/top_level.txt
sitemapa-0.1.4.dist-info/RECORD
