Metadata-Version: 2.1
Name: sitemapa
Version: 0.1.4
Summary: Create advanced sitemaps easily
Home-page: https://abstractkitchen.com/blog/sitemaps-for-devs/
Author: Dmitry S.
Author-email: <dmitry@abstractkitchen.com>
Keywords: python,sitemap,
Classifier: Development Status :: 5 - Production/Stable
Classifier: Programming Language :: Python
Classifier: Programming Language :: Python :: 3
License-File: LICENSE
